galv_harvester/README.md
galv_harvester/__about__.py
galv_harvester/__init__.py
galv_harvester/__main__.py
galv_harvester/api.py
galv_harvester/harvest.py
galv_harvester/plugins.py
galv_harvester/run.py
galv_harvester/settings.py
galv_harvester/start.py
galv_harvester/utils.py
galv_harvester/parse/__init__.py
galv_harvester/parse/arbin.py
galv_harvester/parse/biologic_input_file.py
galv_harvester/parse/delimited_input_file.py
galv_harvester/parse/exceptions.py
galv_harvester/parse/input_file.py
galv_harvester/parse/ivium_input_file.py
galv_harvester/parse/maccor_input_file.py
galv_harvester-1.3.5.dist-info/METADATA
galv_harvester-1.3.5.dist-info/WHEEL
galv_harvester-1.3.5.dist-info/entry_points.txt
galv_harvester-1.3.5.dist-info/licenses/LICENSE
galv_harvester-1.3.5.dist-info/RECORD
