Metadata-Version: 2.4
Name: galv-harvester
Version: 1.3.5
Project-URL: Documentation, https://github.com/galv-team/galv-harvester#readme
Project-URL: Issues, https://github.com/galv-team/galv-harvester/issues
Project-URL: Source, https://github.com/galv-team/galv-harvester
Author-email: Matt Jaquiery <matt.jaquiery@dtc.ox.ac.uk>
License: Copyright  (c) 2020-2023, The Chancellor, Masters and Scholars of the University
License-File: LICENSE
Keywords: battery,cycler,galv
Classifier: Development Status :: 4 - Beta
Classifier: Intended Audience :: Science/Research
Classifier: License :: OSI Approved :: BSD License
Classifier: Natural Language :: English
Classifier: Programming Language :: Python
Classifier: Programming Language :: Python :: 3.9
Classifier: Programming Language :: Python :: 3.10
Classifier: Programming Language :: Python :: 3.11
Classifier: Programming Language :: Python :: 3.12
Classifier: Programming Language :: Python :: Implementation :: CPython
Classifier: Programming Language :: Python :: Implementation :: PyPy
Requires-Python: >=3.9
Requires-Dist: click~=8.1.3
Requires-Dist: dask[complete]==2024.4.2
Requires-Dist: datashader==0.16.1
Requires-Dist: fastnumbers~=5.1.0
Requires-Dist: galvani~=0.4.1
Requires-Dist: holoviews==1.18.3
Requires-Dist: matplotlib==3.9.0
Requires-Dist: maya~=0.6.1
Requires-Dist: pandas~=2.2.1
Requires-Dist: psutil~=5.9.4
Requires-Dist: requests~=2.32.0
Requires-Dist: xlrd~=2.0.1
